AdonisAI/CONSTANT.py
AdonisAI/__init__.py
AdonisAI/features_default.py
AdonisAI/auth/__init__.py
AdonisAI/brain_nlu/__init__.py
AdonisAI/brain_nlu/decision_maker_api.py
AdonisAI/features/__init__.py
AdonisAI/features/chatbot/__init__.py
AdonisAI/features/chatbot/chatbot.py
AdonisAI/features/click_photo/__init__.py
AdonisAI/features/click_photo/click_photo.py
AdonisAI/features/covid_cases/__init__.py
AdonisAI/features/covid_cases/covid_cases.py
AdonisAI/features/date_time/__init__.py
AdonisAI/features/date_time/date_time.py
AdonisAI/features/games/__init__.py
AdonisAI/features/games/games.py
AdonisAI/features/internet_speed_test/__init__.py
AdonisAI/features/internet_speed_test/internet_speed_test.py
AdonisAI/features/joke/__init__.py
AdonisAI/features/joke/joke.py
AdonisAI/features/launch_app/__init__.py
AdonisAI/features/launch_app/launch_app.py
AdonisAI/features/news/__init__.py
AdonisAI/features/news/news.py
AdonisAI/features/screenshot/__init__.py
AdonisAI/features/screenshot/screenshot.py
AdonisAI/features/send_email/__init__.py
AdonisAI/features/send_email/send_email.py
AdonisAI/features/tell_me_about/__init__.py
AdonisAI/features/tell_me_about/tell_me_about.py
AdonisAI/features/weather/__init__.py
AdonisAI/features/weather/weather.py
AdonisAI/features/website_open/__init__.py
AdonisAI/features/website_open/website_open.py
AdonisAI/features/whatsapp_message/__init__.py
AdonisAI/features/whatsapp_message/whatsapp_message.py
AdonisAI/features/youtube_play/__init__.py
AdonisAI/features/youtube_play/youtube_play.py
AdonisAI/features/youtube_video_downloader/__init__.py
AdonisAI/features/youtube_video_downloader/youtube_video_downloader.py
AdonisAI/services/__init__.py
AdonisAI/services/asr_deepspeech_streaming/__init__.py
AdonisAI/services/asr_deepspeech_streaming/streaming.py
AdonisAI/services/mic_input_ai/__init__.py
AdonisAI/services/mic_input_ai/mic_input_ai.py
AdonisAI/services/speech_to_text_google/__init__.py
AdonisAI-1.7.dist-info/METADATA
AdonisAI-1.7.dist-info/WHEEL
AdonisAI-1.7.dist-info/top_level.txt
AdonisAI-1.7.dist-info/RECORD
