Metadata-Version: 2.1
Name: AdonisAI
Version: 1.7
Summary: AdonisAI is python library to build your own AI virtual assistant with natural language processing.
Home-page: https://github.com/Dipeshpal/Adonis
Author: Dipesh
Author-email: dipeshpal17@gmail.com
License: UNKNOWN
Project-URL: Documentation, https://github.com/Dipeshpal/Jarvis_AI
Project-URL: Donate, https://www.buymeacoffee.com/dipeshpal
Project-URL: Say Thanks!, https://youtube.com/techportofficial
Project-URL: Source, https://github.com/Dipeshpal/Jarvis_AI
Platform: UNKNOWN
Classifier: Programming Language :: Python :: 3
Classifier: License :: OSI Approved :: MIT License
Classifier: Operating System :: OS Independent
Requires-Python: >=3.6
Requires-Dist: pyaudio
Requires-Dist: SpeechRecognition
Requires-Dist: gtts
Requires-Dist: lazyme
Requires-Dist: torch
Requires-Dist: joblib
Requires-Dist: phonetics
Requires-Dist: fuzzywuzzy
Requires-Dist: requests
Requires-Dist: librosa
Requires-Dist: transformers
Requires-Dist: playsound (==1.2.2)
Requires-Dist: pyttsx3
Requires-Dist: python-Levenshtein
Requires-Dist: shutup
Requires-Dist: download
Requires-Dist: pyjokes
Requires-Dist: spacy
Requires-Dist: beautifulsoup4 (==4.9.3)
Requires-Dist: wikipedia
Requires-Dist: deepspeech
Requires-Dist: deepspeech-gpu
Requires-Dist: webrtcvad
Requires-Dist: halo
Requires-Dist: scipy
Requires-Dist: pywhatkit
Requires-Dist: flask
Requires-Dist: regex
Requires-Dist: numpy
Requires-Dist: textdistance[extras]
Requires-Dist: opencv-python (==4.5.5.64)
Requires-Dist: pyscreenshot (==3.0)
Requires-Dist: speedtest-cli (==2.1.3)
Requires-Dist: pytube (==12.0.0)
Requires-Dist: pycountry (==22.3.5)
